ixian/__init__.py
ixian/builder.py
ixian/config.py
ixian/exceptions.py
ixian/logger.py
ixian/module.py
ixian/runner.py
ixian/task.py
ixian/version.py
ixian/check/__init__.py
ixian/check/checker.py
ixian/modules/__init__.py
ixian/modules/core/__init__.py
ixian/modules/core/tasks.py
ixian/modules/filesystem/__init__.py
ixian/modules/filesystem/file_hash.py
ixian/tests/__init__.py
ixian/tests/conftest.py
ixian/tests/fake.py
ixian/tests/mock_checker.py
ixian/tests/test_builder.py
ixian/tests/test_checker.py
ixian/tests/test_config.py
ixian/tests/test_module.py
ixian/tests/test_runner.py
ixian/tests/test_task.py
ixian/tests/mocks/__init__.py
ixian/tests/mocks/modules/__init__.py
ixian/tests/mocks/modules/config_path_does_not_exist/__init__.py
ixian/tests/mocks/modules/config_path_invalid/__init__.py
ixian/tests/mocks/modules/empty_tasks_module/__init__.py
ixian/tests/mocks/modules/empty_tasks_module/config.py
ixian/tests/mocks/modules/empty_tasks_module/tasks.py
ixian/tests/mocks/modules/functional/__init__.py
ixian/tests/mocks/modules/functional/config.py
ixian/tests/mocks/modules/functional/tasks.py
ixian/tests/mocks/modules/no_config/__init__.py
ixian/tests/mocks/modules/no_config/tasks.py
ixian/tests/mocks/modules/no_name/__init__.py
ixian/tests/mocks/modules/no_options/__init__.py
ixian/tests/mocks/modules/no_tasks/__init__.py
ixian/tests/mocks/modules/no_tasks/config.py
ixian/tests/mocks/modules/no_tasks/tasks.py
ixian/tests/mocks/modules/task_load_error/__init__.py
ixian/tests/mocks/modules/task_load_error/config.py
ixian/tests/mocks/modules/task_load_error/tasks.py
ixian/tests/mocks/modules/task_path_does_not_exist/__init__.py
ixian/tests/mocks/modules/task_path_does_not_exist/config.py
ixian/tests/mocks/workspaces/__init__.py
ixian/tests/mocks/workspaces/functional/__init__.py
ixian/tests/mocks/workspaces/functional/ixian.py
ixian/tests/mocks/workspaces/ixian_py_no_init/__init__.py
ixian/tests/mocks/workspaces/ixian_py_no_init/ixian.py
ixian-0.2.8.dist-info/AUTHORS
ixian-0.2.8.dist-info/LICENSE-2.0.txt
ixian-0.2.8.dist-info/METADATA
ixian-0.2.8.dist-info/NOTICE
ixian-0.2.8.dist-info/WHEEL
ixian-0.2.8.dist-info/entry_points.txt
ixian-0.2.8.dist-info/pbr.json
ixian-0.2.8.dist-info/top_level.txt
ixian-0.2.8.dist-info/RECORD
