Metadata-Version: 2.1
Name: ixian
Version: 0.2.8
Summary: Task tool with make-like features.
Home-page: https://github.com/kreneskyp/ixian
Author: Peter Krenesky
Author-email: kreneskyp@gmail.com
Maintainer: Peter Krenesky
Maintainer-email: kreneskyp@gmail.com
License: Apache License, Version 2.0
Keywords: tasks, shovel, rake, make, ixian, ix
Platform: UNKNOWN
Classifier: Intended Audience :: Developers
Classifier: License :: OSI Approved :: Apache Software License
Classifier: Programming Language :: Python
Classifier: Programming Language :: Python :: 3
Classifier: Programming Language :: Python :: 3.6
Classifier: Programming Language :: Python :: 3.7
Classifier: Programming Language :: Python :: 3.8
Classifier: Development Status :: 4 - Beta
Classifier: Operating System :: OS Independent
Classifier: Topic :: Software Development :: Build Tools
Requires-Dist: argcomplete (==1.9.4)
Requires-Dist: argparse (==1.4.0)
Requires-Dist: string-color (==1.2.1)
